sunau/__init__.py
standard_sunau-3.12.2.dist-info/LICENSE
standard_sunau-3.12.2.dist-info/METADATA
standard_sunau-3.12.2.dist-info/WHEEL
standard_sunau-3.12.2.dist-info/top_level.txt
standard_sunau-3.12.2.dist-info/RECORD
