Metadata-Version: 2.1
Name: standard-sunau
Version: 3.12.2
Summary: Standard library sunau redistribution. "dead battery".
Author-email: Python Devleopers <python-deadlib@youknowone.org>
License: Copyright © 2001-2023 Python Software Foundation; All Rights Reserved
Project-URL: Homepage, https://github.com/youknowone/python-deadlib
Keywords: stdlib
Classifier: License :: OSI Approved :: Python Software Foundation License
Classifier: Topic :: Software Development :: Libraries
Classifier: Programming Language :: Python :: 3
License-File: LICENSE
